{
  "raw": "{\"alternate_locations\":{\"servers\":[{\"server\":\"dn711008.ca.archive.org\",\"dir\":\"/0/items/nouvellefrancec00groogoog\"},{\"server\":\"dn760002.eu.archive.org\",\"dir\":\"/0/items/nouvellefrancec00groogoog\"}],\"workable\":[{\"server\":\"dn711008.ca.archive.org\",\"dir\":\"/0/items/nouvellefrancec00groogoog\"},{\"server\":\"dn760002.eu.archive.org\",\"dir\":\"/0/items/nouvellefrancec00groogoog\"}]},\"created\":1784255547,\"d1\":\"ia601608.us.archive.org\",\"d2\":\"ia801608.us.archive.org\",\"dir\":\"/27/items/nouvellefrancec00groogoog\",\"files\":[{\"name\":\"__ia_thumb.jpg\",\"source\":\"original\",\"mtime\":\"1577293282\",\"size\":\"8951\",\"md5\":\"ae41b0228a53f4c0f3a0e7e42d5bc42a\",\"crc32\":\"216a397b\",\"sha1\":\"bb3f90cb1bb5b223f06e6a0de79e7d693f91674c\",\"format\":\"Item Tile\",\"rotation\":\"0\"},{\"name\":\"nouvellefrancec00groogoog.djvu\",\"source\":\"derivative\",\"format\":\"DjVu\",\"original\":\"nouvellefrancec00groogoog_djvu.xml\",\"md5\":\"7786f2c887db9cadd4fee703343c6833\",\"mtime\":\"1230976988\",\"size\":\"11984391\",\"crc32\":\"93d0d80f\",\"sha1\":\"2a63a7538d471222ea0708d78cd06f03a8a060ea\"},{\"name\":\"nouvellefrancec00groogoog.gif\",\"source\":\"derivative\",\"format\":\"Animated GIF\",\"original\":\"nouvellefrancec00groogoog_tif.zip\",\"md5\":\"5fda8d06a7c7770ac7f32df65a6f5148\",\"mtime\":\"1209987836\",\"size\":\"124759\",\"crc32\":\"e5bbf1c3\",\"sha1\":\"4c0272fb6c3ee49330eb1babc98e56318ad01bb1\"},{\"name\":\"nouvellefrancec00groogoog.pdf\",\"source\":\"original\",\"format\":\"Image Container PDF\",\"original-name\":\"Nouvelle_France.pdf?id=sH4BAAAAMAAJ&output=pdf&sig=IiEeSm2ntGGvl6AriVcW8Cv5B0I\",\"size\":\"11824105\",\"atime\":\"1192311092\",\"mtime\":\"1192311088\",\"ctime\":\"1192311092\",\"md5\":\"bcf97018a6aba04a0f5632053471f564\",\"sha1\":\"9bc7d55569441dddf6d23660643c9e6769b98f47\",\"crc32\":\"be72d602\"},{\"name\":\"nouvellefrancec00groogoog_abbyy.gz\",\"source\":\"derivative\",\"format\":\"Abbyy GZ\",\"original\":\"nouvellefrancec00groogoog_tif.zip\",\"md5\":\"3f9ddafff4fd34ecd1537c972fd5f7b6\",\"mtime\":\"1230976389\",\"size\":\"10545324\",\"crc32\":\"f79918dc\",\"sha1\":\"90e0ccb1f4bcde109bc6eac075bc9e0e78894fff\"},{\"name\":\"nouvellefrancec00groogoog_archive.torrent\",\"source\":\"metadata\",\"btih\":\"f7fecf32403d0c8c822ae83ef114768d43492a66\",\"mtime\":\"1577293283\",\"size\":\"7023\",\"md5\":\"41f78c0b4793e342244ca0e1ac35978e\",\"crc32\":\"bd7f72be\",\"sha1\":\"939adffb653458c9e508d0f7cc9a1c67c8c96f53\",\"format\":\"Archive BitTorrent\"},{\"name\":\"nouvellefrancec00groogoog_desc.html\",\"source\":\"original\",\"format\":\"Metadata\",\"original-name\":\"books?id=sH4BAAAAMAAJ&oe=UTF-8\",\"size\":\"30838\",\"atime\":\"1184647602\",\"mtime\":\"1184647289\",\"ctime\":\"1184647602\",\"md5\":\"f43a78b437ac78f9ad9fd2cfd2edb826\",\"sha1\":\"92f978b2453d51ce78e8ffe1794c67f2d6fb15d1\",\"crc32\":\"f169d56d\"},{\"name\":\"nouvellefrancec00groogoog_djvu.txt\",\"source\":\"derivative\",\"format\":\"DjVuTXT\",\"original\":\"nouvellefrancec00groogoog.djvu\",\"md5\":\"2809dad78215d0fd5ef0086c9086f7f7\",\"mtime\":\"1230977017\",\"size\":\"680874\",\"crc32\":\"799d0310\",\"sha1\":\"609dc2cf212916a139517400ee6f56c8d6cec42b\"},{\"name\":\"nouvellefrancec00groogoog_djvu.xml\",\"source\":\"derivative\",\"format\":\"Djvu XML\",\"original\":\"nouvellefrancec00groogoog_abbyy.gz\",\"md5\":\"6bfbb4060678a873fa5f81178fad3d04\",\"mtime\":\"1230976660\",\"size\":\"5975604\",\"crc32\":\"f7b3a07c\",\"sha1\":\"939f86457716dbb0136a370b23c6381aba88c25d\"},{\"name\":\"nouvellefrancec00groogoog_files.xml\",\"source\":\"metadata\",\"format\":\"Metadata\",\"md5\":\"197f6074cc102a6b642bec8097b920a7\",\"summation\":\"md5\"},{\"name\":\"nouvellefrancec00groogoog_meta.xml\",\"source\":\"metadata\",\"format\":\"Metadata\",\"mtime\":\"1577293281\",\"size\":\"1441\",\"md5\":\"9d40be16676bbb9c759a84403471a2f3\",\"crc32\":\"57330cc5\",\"sha1\":\"5f7d081aeb350dab75ca227a3c1dda886ee1ff84\"},{\"name\":\"nouvellefrancec00groogoog_scandata.xml\",\"source\":\"derivative\",\"format\":\"Scandata\",\"original\":\"nouvellefrancec00groogoog_djvu.xml\",\"md5\":\"0f6ddabf7e706af7366e8771637cd8c2\",\"mtime\":\"1243722970\",\"size\":\"126411\",\"crc32\":\"ed110d6\",\"sha1\":\"795d73815e49abe4b9f6fbcd045bb85758a37a9b\"},{\"name\":\"nouvellefrancec00groogoog_tif.zip\",\"source\":\"derivative\",\"format\":\"Single Page Processed TIFF ZIP\",\"original\":\"nouvellefrancec00groogoog.pdf\",\"md5\":\"4e5ac64c82b139ae68fcc819a10e94f3\",\"mtime\":\"1209987811\",\"size\":\"58087529\",\"crc32\":\"7cdb25bf\",\"sha1\":\"7edd408ce6f2a1ba44ce42eb92e14d4926326a2b\",\"filecount\":\"421\"}],\"files_count\":13,\"item_last_updated\":1680332042,\"item_size\":99397250,\"metadata\":{\"publisher\":\"Soci\\u00e9t\\u00e9 g\\u00e9n\\u00e9rale de librairie catholique\",\"identifier\":\"nouvellefrancec00groogoog\",\"scanner\":\"google\",\"title\":\"Nouvelle-France: Colonie libre de Port-Breton, Oc\\u00e9anie\",\"creator\":\"P. de Groote\",\"mediatype\":\"texts\",\"collection\":\"americana\",\"possible-copyright-status\":\"NOT_IN_COPYRIGHT\",\"identifier-access\":\"http://www.archive.org/details/nouvellefrancec00groogoog\",\"year\":\"1880\",\"date\":\"1880\",\"scandate\":\"20060711\",\"copyright-region\":\"US\",\"description\":\"Book digitized by Google from the library of the University of Michigan and uploaded to the Internet Archive by user tpb.\",\"identifier-ark\":\"ark:/13960/t3vt1qk1t\",\"imagecount\":\"421\",\"publicdate\":\"2008-05-05 18:02:08\",\"source\":\"http://books.google.com/books?id=sH4BAAAAMAAJ&oe=UTF-8\",\"contributor\":\"University of Michigan\",\"sponsor\":\"Google\",\"uploader\":\"tpb\",\"language\":\"French\",\"ocr\":\"ABBYY FineReader 8.0\",\"repub_state\":\"4\",\"backup_location\":\"ia903601_33\",\"openlibrary_edition\":\"OL20456692M\",\"openlibrary_work\":\"OL13118838W\",\"addeddate\":\"2008-05-05 18:02:08\"},\"server\":\"ia601608.us.archive.org\",\"uniq\":544511147,\"workable_servers\":[\"ia601608.us.archive.org\",\"ia801608.us.archive.org\"]}",
  "retrievedAt": "2026-07-17T02:32:28.019Z",
  "endpoint": "https://archive.org/metadata/nouvellefrancec00groogoog",
  "normalizationVersion": 1
}
